multipart_base_n/__init__.py
multipart_base_n/__main__.py
multipart_base_n_converter-0.1.0.dist-info/METADATA
multipart_base_n_converter-0.1.0.dist-info/RECORD
multipart_base_n_converter-0.1.0.dist-info/WHEEL
multipart_base_n_converter-0.1.0.dist-info/entry_points.txt
multipart_base_n_converter-0.1.0.dist-info/top_level.txt
