Metadata-Version: 2.1
Name: multipart-base-n-converter
Version: 0.1.0
Summary: convert a number to string with multiple parts based on the given string base
Home-page: https://github.com/weaming/multipart-base-n-converter
Author: weaming
Author-email: garden.yuen@gmail.com
License: UNKNOWN
Project-URL: Source, https://github.com/weaming/multipart-base-n-converter
Project-URL: Bug Reports, https://github.com/weaming/multipart-base-n-converter
Keywords: math
Platform: UNKNOWN
